[
  {
    "rcept_no": "20220516000629",
    "reprt_code": "11013",
    "bsns_year": "2022",
    "corp_code": "00493510",
    "sj_div": "BS",
    "sj_nm": "재무상태표",
    "account_id": "ifrs-full_CurrentAssets",
    "account_nm": "유동자산",
    "account_detail": "-",
    "thstrm_nm": "제 23 기 1분기말",
    "thstrm_amount": "70164660667",
    "frmtrm_nm": "제 22 기말",
    "frmtrm_amount": "66733528255",
    "ord": "1",
    "currency": "KRW"
  },
  {
    "rcept_no": "20220516000629",
    "reprt_code": "11013",
    "bsns_year": "2022",
    "corp_code": "00493510",
    "sj_div": "BS",
    "sj_nm": "재무상태표",
    "account_id": "ifrs-full_CashAndCashEquivalents",
    "account_nm": "현금및현금성자산",
    "account_detail": "-",
    "thstrm_nm": "제 23 기 1분기말",
    "thstrm_amount": "2053839915",
    "frmtrm_nm": "제 22 기말",
    "frmtrm_amount": "1280972255",
    "ord": "2",
    "currency": "KRW"
  },
  {
    "rcept_no": "20220516000629",
    "reprt_code": "11013",
    "bsns_year": "2022",
    "corp_code": "00493510",
    "sj_div": "BS",
    "sj_nm": "재무상태표",
    "account_id": "dart_ShortTermDepositsNotClassifiedAsCashEquivalents",
    "account_nm": "단기금융상품",
    "account_detail": "-",
    "thstrm_nm": "제 23 기 1분기말",
    "thstrm_amount": "760000000",
    "frmtrm_nm": "제 22 기말",
    "frmtrm_amount": "640000000",
    "ord": "3",
    "currency": "KRW"
  },
  {
    "rcept_no": "20220516000629",
    "reprt_code": "11013",
    "bsns_year": "2022",
    "corp_code": "00493510",
    "sj_div": "BS",
    "sj_nm": "재무상태표",
    "account_id": "dart_ShortTermTradeReceivable",
    "account_nm": "매출채권",
    "account_detail": "-",
    "thstrm_nm": "제 23 기 1분기말",
    "thstrm_amount": "38068614279",
    "frmtrm_nm": "제 22 기말",
    "frmtrm_amount": "38374521156",
    "ord": "4",
    "currency": "KRW"
  },
  {
    "rcept_no": "20220516000629",
    "reprt_code": "11013",
    "bsns_year": "2022",
    "corp_code": "00493510",
    "sj_div": "BS",
    "sj_nm": "재무상태표",
    "account_id": "-표준계정코드 미사용-",
    "account_nm": "기타수취채권",
    "account_detail": "-",
    "thstrm_nm": "제 23 기 1분기말",
    "thstrm_amount": "3924410480",
    "frmtrm_nm": "제 22 기말",
    "frmtrm_amount": "3288250474",
    "ord": "5",
    "currency": "KRW"
  },
  {
    "rcept_no": "20220516000629",
    "reprt_code": "11013",
    "bsns_year": "2022",
    "corp_code": "00493510",
    "sj_div": "BS",
    "sj_nm": "재무상태표",
    "account_id": "dart_OtherCurrentAssets",
    "account_nm": "기타유동자산",
    "account_detail": "-",
    "thstrm_nm": "제 23 기 1분기말",
    "thstrm_amount": "3627671604",
    "frmtrm_nm": "제 22 기말",
    "frmtrm_amount": "1912857816",
    "ord": "6",
    "currency": "KRW"
  },
  {
    "rcept_no": "20220516000629",
    "reprt_code": "11013",
    "bsns_year": "2022",
    "corp_code": "00493510",
    "sj_div": "BS",
    "sj_nm": "재무상태표",
    "account_id": "ifrs-full_Inventories",
    "account_nm": "재고자산",
    "account_detail": "-",
    "thstrm_nm": "제 23 기 1분기말",
    "thstrm_amount": "21730124389",
    "frmtrm_nm": "제 22 기말",
    "frmtrm_amount": "21236926554",
    "ord": "7",
    "currency": "KRW"
  },
  {
    "rcept_no": "20220516000629",
    "reprt_code": "11013",
    "bsns_year": "2022",
    "corp_code": "00493510",
    "sj_div": "BS",
    "sj_nm": "재무상태표",
    "account_id": "ifrs-full_NoncurrentAssets",
    "account_nm": "비유동자산",
    "account_detail": "-",
    "thstrm_nm": "제 23 기 1분기말",
    "thstrm_amount": "97969507652",
    "frmtrm_nm": "제 22 기말",
    "frmtrm_amount": "97909707969",
    "ord": "8",
    "currency": "KRW"
  },
  {
    "rcept_no": "20220516000629",
    "reprt_code": "11013",
    "bsns_year": "2022",
    "corp_code": "00493510",
    "sj_div": "BS",
    "sj_nm": "재무상태표",
    "account_id": "dart_LongTermDepositsNotClassifiedAsCashEquivalents",
    "account_nm": "장기금융상품",
    "account_detail": "-",
    "thstrm_nm": "제 23 기 1분기말",
    "thstrm_amount": "520000000",
    "frmtrm_nm": "제 22 기말",
    "frmtrm_amount": "340000000",
    "ord": "9",
    "currency": "KRW"
  },
  {
    "rcept_no": "20220516000629",
    "reprt_code": "11013",
    "bsns_year": "2022",
    "corp_code": "00493510",
    "sj_div": "BS",
    "sj_nm": "재무상태표",
    "account_id": "ifrs-full_PropertyPlantAndEquipment",
    "account_nm": "유형자산",
    "account_detail": "-",
    "thstrm_nm": "제 23 기 1분기말",
    "thstrm_amount": "95710939405",
    "frmtrm_nm": "제 22 기말",
    "frmtrm_amount": "95520541970",
    "ord": "10",
    "currency": "KRW"
  },
  {
    "rcept_no": "20220516000629",
    "reprt_code": "11013",
    "bsns_year": "2022",
    "corp_code": "00493510",
    "sj_div": "BS",
    "sj_nm": "재무상태표",
    "account_id": "ifrs-full_IntangibleAssetsOtherThanGoodwill",
    "account_nm": "무형자산",
    "account_detail": "-",
    "thstrm_nm": "제 23 기 1분기말",
    "thstrm_amount": "808035996",
    "frmtrm_nm": "제 22 기말",
    "frmtrm_amount": "857941490",
    "ord": "11",
    "currency": "KRW"
  },
  {
    "rcept_no": "20220516000629",
    "reprt_code": "11013",
    "bsns_year": "2022",
    "corp_code": "00493510",
    "sj_div": "BS",
    "sj_nm": "재무상태표",
    "account_id": "ifrs-full_DeferredTaxAssets",
    "account_nm": "이연법인세자산",
    "account_detail": "-",
    "thstrm_nm": "제 23 기 1분기말",
    "thstrm_amount": "14066711",
    "frmtrm_nm": "제 22 기말",
    "frmtrm_amount": "27191489",
    "ord": "12",
    "currency": "KRW"
  },
  {
    "rcept_no": "20220516000629",
    "reprt_code": "11013",
    "bsns_year": "2022",
    "corp_code": "00493510",
    "sj_div": "BS",
    "sj_nm": "재무상태표",
    "account_id": "dart_OtherNonCurrentAssets",
    "account_nm": "기타비유동자산",
    "account_detail": "-",
    "thstrm_nm": "제 23 기 1분기말",
    "thstrm_amount": "916465540",
    "frmtrm_nm": "제 22 기말",
    "frmtrm_amount": "1164033020",
    "ord": "13",
    "currency": "KRW"
  },
  {
    "rcept_no": "20220516000629",
    "reprt_code": "11013",
    "bsns_year": "2022",
    "corp_code": "00493510",
    "sj_div": "BS",
    "sj_nm": "재무상태표",
    "account_id": "ifrs-full_Assets",
    "account_nm": "자산총계",
    "account_detail": "-",
    "thstrm_nm": "제 23 기 1분기말",
    "thstrm_amount": "168134168319",
    "frmtrm_nm": "제 22 기말",
    "frmtrm_amount": "164643236224",
    "ord": "14",
    "currency": "KRW"
  },
  {
    "rcept_no": "20220516000629",
    "reprt_code": "11013",
    "bsns_year": "2022",
    "corp_code": "00493510",
    "sj_div": "BS",
    "sj_nm": "재무상태표",
    "account_id": "ifrs-full_CurrentLiabilities",
    "account_nm": "유동부채",
    "account_detail": "-",
    "thstrm_nm": "제 23 기 1분기말",
    "thstrm_amount": "98436338066",
    "frmtrm_nm": "제 22 기말",
    "frmtrm_amount": "102634241207",
    "ord": "16",
    "currency": "KRW"
  },
  {
    "rcept_no": "20220516000629",
    "reprt_code": "11013",
    "bsns_year": "2022",
    "corp_code": "00493510",
    "sj_div": "BS",
    "sj_nm": "재무상태표",
    "account_id": "ifrs-full_TradeAndOtherCurrentPayables",
    "account_nm": "매입채무",
    "account_detail": "-",
    "thstrm_nm": "제 23 기 1분기말",
    "thstrm_amount": "35299502922",
    "frmtrm_nm": "제 22 기말",
    "frmtrm_amount": "36042999992",
    "ord": "17",
    "currency": "KRW"
  },
  {
    "rcept_no": "20220516000629",
    "reprt_code": "11013",
    "bsns_year": "2022",
    "corp_code": "00493510",
    "sj_div": "BS",
    "sj_nm": "재무상태표",
    "account_id": "ifrs-full_ShorttermBorrowings",
    "account_nm": "단기차입금",
    "account_detail": "-",
    "thstrm_nm": "제 23 기 1분기말",
    "thstrm_amount": "53014160615",
    "frmtrm_nm": "제 22 기말",
    "frmtrm_amount": "53184299922",
    "ord": "18",
    "currency": "KRW"
  },
  {
    "rcept_no": "20220516000629",
    "reprt_code": "11013",
    "bsns_year": "2022",
    "corp_code": "00493510",
    "sj_div": "BS",
    "sj_nm": "재무상태표",
    "account_id": "-표준계정코드 미사용-",
    "account_nm": "기타지급채무",
    "account_detail": "-",
    "thstrm_nm": "제 23 기 1분기말",
    "thstrm_amount": "5719613597",
    "frmtrm_nm": "제 22 기말",
    "frmtrm_amount": "5870231622",
    "ord": "19",
    "currency": "KRW"
  },
  {
    "rcept_no": "20220516000629",
    "reprt_code": "11013",
    "bsns_year": "2022",
    "corp_code": "00493510",
    "sj_div": "BS",
    "sj_nm": "재무상태표",
    "account_id": "ifrs-full_OtherCurrentFinancialLiabilities",
    "account_nm": "기타유동금융부채",
    "account_detail": "-",
    "thstrm_nm": "제 23 기 1분기말",
    "thstrm_amount": "3611433327",
    "frmtrm_nm": "제 22 기말",
    "frmtrm_amount": "6784177869",
    "ord": "20",
    "currency": "KRW"
  },
  {
    "rcept_no": "20220516000629",
    "reprt_code": "11013",
    "bsns_year": "2022",
    "corp_code": "00493510",
    "sj_div": "BS",
    "sj_nm": "재무상태표",
    "account_id": "ifrs-full_CurrentProvisions",
    "account_nm": "유동충당부채",
    "account_detail": "-",
    "thstrm_nm": "제 23 기 1분기말",
    "thstrm_amount": "195825359",
    "frmtrm_nm": "제 22 기말",
    "frmtrm_amount": "232145214",
    "ord": "21",
    "currency": "KRW"
  },
  {
    "rcept_no": "20220516000629",
    "reprt_code": "11013",
    "bsns_year": "2022",
    "corp_code": "00493510",
    "sj_div": "BS",
    "sj_nm": "재무상태표",
    "account_id": "dart_OtherCurrentLiabilities",
    "account_nm": "기타유동부채",
    "account_detail": "-",
    "thstrm_nm": "제 23 기 1분기말",
    "thstrm_amount": "565788094",
    "frmtrm_nm": "제 22 기말",
    "frmtrm_amount": "486940249",
    "ord": "22",
    "currency": "KRW"
  },
  {
    "rcept_no": "20220516000629",
    "reprt_code": "11013",
    "bsns_year": "2022",
    "corp_code": "00493510",
    "sj_div": "BS",
    "sj_nm": "재무상태표",
    "account_id": "ifrs-full_CurrentLeaseLiabilities",
    "account_nm": "유동리스부채",
    "account_detail": "-",
    "thstrm_nm": "제 23 기 1분기말",
    "thstrm_amount": "30014152",
    "frmtrm_nm": "제 22 기말",
    "frmtrm_amount": "33446339",
    "ord": "23",
    "currency": "KRW"
  },
  {
    "rcept_no": "20220516000629",
    "reprt_code": "11013",
    "bsns_year": "2022",
    "corp_code": "00493510",
    "sj_div": "BS",
    "sj_nm": "재무상태표",
    "account_id": "ifrs-full_NoncurrentLiabilities",
    "account_nm": "비유동부채",
    "account_detail": "-",
    "thstrm_nm": "제 23 기 1분기말",
    "thstrm_amount": "10074630076",
    "frmtrm_nm": "제 22 기말",
    "frmtrm_amount": "9679128891",
    "ord": "24",
    "currency": "KRW"
  },
  {
    "rcept_no": "20220516000629",
    "reprt_code": "11013",
    "bsns_year": "2022",
    "corp_code": "00493510",
    "sj_div": "BS",
    "sj_nm": "재무상태표",
    "account_id": "dart_LongTermBorrowingsGross",
    "account_nm": "장기차입금",
    "account_detail": "-",
    "thstrm_nm": "제 23 기 1분기말",
    "thstrm_amount": "6024920721",
    "frmtrm_nm": "제 22 기말",
    "frmtrm_amount": "6563067653",
    "ord": "25",
    "currency": "KRW"
  },
  {
    "rcept_no": "20220516000629",
    "reprt_code": "11013",
    "bsns_year": "2022",
    "corp_code": "00493510",
    "sj_div": "BS",
    "sj_nm": "재무상태표",
    "account_id": "dart_PostemploymentBenefitObligations",
    "account_nm": "확정급여부채",
    "account_detail": "-",
    "thstrm_nm": "제 23 기 1분기말",
    "thstrm_amount": "2037071381",
    "frmtrm_nm": "제 22 기말",
    "frmtrm_amount": "1547316571",
    "ord": "26",
    "currency": "KRW"
  },
  {
    "rcept_no": "20220516000629",
    "reprt_code": "11013",
    "bsns_year": "2022",
    "corp_code": "00493510",
    "sj_div": "BS",
    "sj_nm": "재무상태표",
    "account_id": "ifrs-full_DeferredTaxLiabilities",
    "account_nm": "이연법인세부채",
    "account_detail": "-",
    "thstrm_nm": "제 23 기 1분기말",
    "thstrm_amount": "1803019021",
    "frmtrm_nm": "제 22 기말",
    "frmtrm_amount": "1353790329",
    "ord": "27",
    "currency": "KRW"
  },
  {
    "rcept_no": "20220516000629",
    "reprt_code": "11013",
    "bsns_year": "2022",
    "corp_code": "00493510",
    "sj_div": "BS",
    "sj_nm": "재무상태표",
    "account_id": "ifrs-full_OtherNoncurrentFinancialLiabilities",
    "account_nm": "기타비유동금융부채",
    "account_detail": "-",
    "thstrm_nm": "제 23 기 1분기말",
    "thstrm_amount": "185150000",
    "frmtrm_nm": "제 22 기말",
    "frmtrm_amount": "185150000",
    "ord": "28",
    "currency": "KRW"
  },
  {
    "rcept_no": "20220516000629",
    "reprt_code": "11013",
    "bsns_year": "2022",
    "corp_code": "00493510",
    "sj_div": "BS",
    "sj_nm": "재무상태표",
    "account_id": "ifrs-full_NoncurrentLeaseLiabilities",
    "account_nm": "비유동리스부채",
    "account_detail": "-",
    "thstrm_nm": "제 23 기 1분기말",
    "thstrm_amount": "24468953",
    "frmtrm_nm": "제 22 기말",
    "frmtrm_amount": "29804338",
    "ord": "29",
    "currency": "KRW"
  },
  {
    "rcept_no": "20220516000629",
    "reprt_code": "11013",
    "bsns_year": "2022",
    "corp_code": "00493510",
    "sj_div": "BS",
    "sj_nm": "재무상태표",
    "account_id": "ifrs-full_Liabilities",
    "account_nm": "부채총계",
    "account_detail": "-",
    "thstrm_nm": "제 23 기 1분기말",
    "thstrm_amount": "108510968142",
    "frmtrm_nm": "제 22 기말",
    "frmtrm_amount": "112313370098",
    "ord": "30",
    "currency": "KRW"
  },
  {
    "rcept_no": "20220516000629",
    "reprt_code": "11013",
    "bsns_year": "2022",
    "corp_code": "00493510",
    "sj_div": "BS",
    "sj_nm": "재무상태표",
    "account_id": "ifrs-full_EquityAttributableToOwnersOfParent",
    "account_nm": "지배기업의 소유주에게 귀속되는 자본",
    "account_detail": "-",
    "thstrm_nm": "제 23 기 1분기말",
    "thstrm_amount": "58285111898",
    "frmtrm_nm": "제 22 기말",
    "frmtrm_amount": "51020746524",
    "ord": "32",
    "currency": "KRW"
  },
  {
    "rcept_no": "20220516000629",
    "reprt_code": "11013",
    "bsns_year": "2022",
    "corp_code": "00493510",
    "sj_div": "BS",
    "sj_nm": "재무상태표",
    "account_id": "ifrs-full_IssuedCapital",
    "account_nm": "자본금",
    "account_detail": "-",
    "thstrm_nm": "제 23 기 1분기말",
    "thstrm_amount": "32651784907",
    "frmtrm_nm": "제 22 기말",
    "frmtrm_amount": "32651784907",
    "ord": "33",
    "currency": "KRW"
  },
  {
    "rcept_no": "20220516000629",
    "reprt_code": "11013",
    "bsns_year": "2022",
    "corp_code": "00493510",
    "sj_div": "BS",
    "sj_nm": "재무상태표",
    "account_id": "dart_IssuedCapitalOfCommonStock",
    "account_nm": "자본금",
    "account_detail": "-",
    "thstrm_nm": "제 23 기 1분기말",
    "thstrm_amount": "12104876500",
    "frmtrm_nm": "제 22 기말",
    "frmtrm_amount": "12104876500",
    "ord": "34",
    "currency": "KRW"
  },
  {
    "rcept_no": "20220516000629",
    "reprt_code": "11013",
    "bsns_year": "2022",
    "corp_code": "00493510",
    "sj_div": "BS",
    "sj_nm": "재무상태표",
    "account_id": "-표준계정코드 미사용-",
    "account_nm": "주식발행초과금",
    "account_detail": "-",
    "thstrm_nm": "제 23 기 1분기말",
    "thstrm_amount": "20546908407",
    "frmtrm_nm": "제 22 기말",
    "frmtrm_amount": "20546908407",
    "ord": "35",
    "currency": "KRW"
  },
  {
    "rcept_no": "20220516000629",
    "reprt_code": "11013",
    "bsns_year": "2022",
    "corp_code": "00493510",
    "sj_div": "BS",
    "sj_nm": "재무상태표",
    "account_id": "ifrs-full_RetainedEarnings",
    "account_nm": "이익잉여금",
    "account_detail": "-",
    "thstrm_nm": "제 23 기 1분기말",
    "thstrm_amount": "13988491808",
    "frmtrm_nm": "제 22 기말",
    "frmtrm_amount": "6611954196",
    "ord": "36",
    "currency": "KRW"
  },
  {
    "rcept_no": "20220516000629",
    "reprt_code": "11013",
    "bsns_year": "2022",
    "corp_code": "00493510",
    "sj_div": "BS",
    "sj_nm": "재무상태표",
    "account_id": "dart_OtherComprehensiveIncomeLossAccumulatedAmount",
    "account_nm": "기타포괄손익누계액",
    "account_detail": "-",
    "thstrm_nm": "제 23 기 1분기말",
    "thstrm_amount": "10796794349",
    "frmtrm_nm": "제 22 기말",
    "frmtrm_amount": "10916944656",
    "ord": "37",
    "currency": "KRW"
  },
  {
    "rcept_no": "20220516000629",
    "reprt_code": "11013",
    "bsns_year": "2022",
    "corp_code": "00493510",
    "sj_div": "BS",
    "sj_nm": "재무상태표",
    "account_id": "dart_ElementsOfOtherStockholdersEquity",
    "account_nm": "자본조정",
    "account_detail": "-",
    "thstrm_nm": "제 23 기 1분기말",
    "thstrm_amount": "848040834",
    "frmtrm_nm": "제 22 기말",
    "frmtrm_amount": "840062765",
    "ord": "38",
    "currency": "KRW"
  },
  {
    "rcept_no": "20220516000629",
    "reprt_code": "11013",
    "bsns_year": "2022",
    "corp_code": "00493510",
    "sj_div": "BS",
    "sj_nm": "재무상태표",
    "account_id": "ifrs-full_NoncontrollingInterests",
    "account_nm": "비지배지분",
    "account_detail": "-",
    "thstrm_nm": "제 23 기 1분기말",
    "thstrm_amount": "1338088279",
    "frmtrm_nm": "제 22 기말",
    "frmtrm_amount": "1309119602",
    "ord": "39",
    "currency": "KRW"
  },
  {
    "rcept_no": "20220516000629",
    "reprt_code": "11013",
    "bsns_year": "2022",
    "corp_code": "00493510",
    "sj_div": "BS",
    "sj_nm": "재무상태표",
    "account_id": "ifrs-full_Equity",
    "account_nm": "자본총계",
    "account_detail": "-",
    "thstrm_nm": "제 23 기 1분기말",
    "thstrm_amount": "59623200177",
    "frmtrm_nm": "제 22 기말",
    "frmtrm_amount": "52329866126",
    "ord": "40",
    "currency": "KRW"
  },
  {
    "rcept_no": "20220516000629",
    "reprt_code": "11013",
    "bsns_year": "2022",
    "corp_code": "00493510",
    "sj_div": "BS",
    "sj_nm": "재무상태표",
    "account_id": "ifrs-full_EquityAndLiabilities",
    "account_nm": "자본과부채총계",
    "account_detail": "-",
    "thstrm_nm": "제 23 기 1분기말",
    "thstrm_amount": "168134168319",
    "frmtrm_nm": "제 22 기말",
    "frmtrm_amount": "164643236224",
    "ord": "41",
    "currency": "KRW"
  },
  {
    "rcept_no": "20220516000629",
    "reprt_code": "11013",
    "bsns_year": "2022",
    "corp_code": "00493510",
    "sj_div": "CIS",
    "sj_nm": "포괄손익계산서",
    "account_id": "ifrs-full_Revenue",
    "account_nm": "매출액",
    "account_detail": "-",
    "thstrm_nm": "제 23 기 1분기",
    "thstrm_amount": "66238418244",
    "thstrm_add_amount": "66238418244",
    "frmtrm_q_nm": "제 22 기 1분기",
    "frmtrm_q_amount": "33222995198",
    "frmtrm_add_amount": "33222995198",
    "ord": "0",
    "currency": "KRW"
  },
  {
    "rcept_no": "20220516000629",
    "reprt_code": "11013",
    "bsns_year": "2022",
    "corp_code": "00493510",
    "sj_div": "CIS",
    "sj_nm": "포괄손익계산서",
    "account_id": "ifrs-full_CostOfSales",
    "account_nm": "매출원가",
    "account_detail": "-",
    "thstrm_nm": "제 23 기 1분기",
    "thstrm_amount": "55350411243",
    "thstrm_add_amount": "55350411243",
    "frmtrm_q_nm": "제 22 기 1분기",
    "frmtrm_q_amount": "32047493595",
    "frmtrm_add_amount": "32047493595",
    "ord": "1",
    "currency": "KRW"
  },
  {
    "rcept_no": "20220516000629",
    "reprt_code": "11013",
    "bsns_year": "2022",
    "corp_code": "00493510",
    "sj_div": "CIS",
    "sj_nm": "포괄손익계산서",
    "account_id": "ifrs-full_GrossProfit",
    "account_nm": "매출총이익",
    "account_detail": "-",
    "thstrm_nm": "제 23 기 1분기",
    "thstrm_amount": "10888007001",
    "thstrm_add_amount": "10888007001",
    "frmtrm_q_nm": "제 22 기 1분기",
    "frmtrm_q_amount": "1175501603",
    "frmtrm_add_amount": "1175501603",
    "ord": "2",
    "currency": "KRW"
  },
  {
    "rcept_no": "20220516000629",
    "reprt_code": "11013",
    "bsns_year": "2022",
    "corp_code": "00493510",
    "sj_div": "CIS",
    "sj_nm": "포괄손익계산서",
    "account_id": "dart_TotalSellingGeneralAdministrativeExpenses",
    "account_nm": "판매비와관리비",
    "account_detail": "-",
    "thstrm_nm": "제 23 기 1분기",
    "thstrm_amount": "4305693496",
    "thstrm_add_amount": "4305693496",
    "frmtrm_q_nm": "제 22 기 1분기",
    "frmtrm_q_amount": "3221877723",
    "frmtrm_add_amount": "3221877723",
    "ord": "3",
    "currency": "KRW"
  },
  {
    "rcept_no": "20220516000629",
    "reprt_code": "11013",
    "bsns_year": "2022",
    "corp_code": "00493510",
    "sj_div": "CIS",
    "sj_nm": "포괄손익계산서",
    "account_id": "dart_OperatingIncomeLoss",
    "account_nm": "영업이익(손실)",
    "account_detail": "-",
    "thstrm_nm": "제 23 기 1분기",
    "thstrm_amount": "6582313505",
    "thstrm_add_amount": "6582313505",
    "frmtrm_q_nm": "제 22 기 1분기",
    "frmtrm_q_amount": "-2046376120",
    "frmtrm_add_amount": "-2046376120",
    "ord": "4",
    "currency": "KRW"
  },
  {
    "rcept_no": "20220516000629",
    "reprt_code": "11013",
    "bsns_year": "2022",
    "corp_code": "00493510",
    "sj_div": "CIS",
    "sj_nm": "포괄손익계산서",
    "account_id": "dart_OtherGains",
    "account_nm": "기타수익",
    "account_detail": "-",
    "thstrm_nm": "제 23 기 1분기",
    "thstrm_amount": "845619805",
    "thstrm_add_amount": "845619805",
    "frmtrm_q_nm": "제 22 기 1분기",
    "frmtrm_q_amount": "477014876",
    "frmtrm_add_amount": "477014876",
    "ord": "5",
    "currency": "KRW"
  },
  {
    "rcept_no": "20220516000629",
    "reprt_code": "11013",
    "bsns_year": "2022",
    "corp_code": "00493510",
    "sj_div": "CIS",
    "sj_nm": "포괄손익계산서",
    "account_id": "dart_OtherLosses",
    "account_nm": "기타비용",
    "account_detail": "-",
    "thstrm_nm": "제 23 기 1분기",
    "thstrm_amount": "110127390",
    "thstrm_add_amount": "110127390",
    "frmtrm_q_nm": "제 22 기 1분기",
    "frmtrm_q_amount": "83424942",
    "frmtrm_add_amount": "83424942",
    "ord": "6",
    "currency": "KRW"
  },
  {
    "rcept_no": "20220516000629",
    "reprt_code": "11013",
    "bsns_year": "2022",
    "corp_code": "00493510",
    "sj_div": "CIS",
    "sj_nm": "포괄손익계산서",
    "account_id": "ifrs-full_FinanceIncome",
    "account_nm": "금융수익",
    "account_detail": "-",
    "thstrm_nm": "제 23 기 1분기",
    "thstrm_amount": "1805470196",
    "thstrm_add_amount": "1805470196",
    "frmtrm_q_nm": "제 22 기 1분기",
    "frmtrm_q_amount": "1697111673",
    "frmtrm_add_amount": "1697111673",
    "ord": "7",
    "currency": "KRW"
  },
  {
    "rcept_no": "20220516000629",
    "reprt_code": "11013",
    "bsns_year": "2022",
    "corp_code": "00493510",
    "sj_div": "CIS",
    "sj_nm": "포괄손익계산서",
    "account_id": "ifrs-full_FinanceCosts",
    "account_nm": "금융비용",
    "account_detail": "-",
    "thstrm_nm": "제 23 기 1분기",
    "thstrm_amount": "1247225717",
    "thstrm_add_amount": "1247225717",
    "frmtrm_q_nm": "제 22 기 1분기",
    "frmtrm_q_amount": "1435163595",
    "frmtrm_add_amount": "1435163595",
    "ord": "8",
    "currency": "KRW"
  },
  {
    "rcept_no": "20220516000629",
    "reprt_code": "11013",
    "bsns_year": "2022",
    "corp_code": "00493510",
    "sj_div": "CIS",
    "sj_nm": "포괄손익계산서",
    "account_id": "ifrs-full_ProfitLossBeforeTax",
    "account_nm": "법인세비용차감전순이익(손실)",
    "account_detail": "-",
    "thstrm_nm": "제 23 기 1분기",
    "thstrm_amount": "7876050399",
    "thstrm_add_amount": "7876050399",
    "frmtrm_q_nm": "제 22 기 1분기",
    "frmtrm_q_amount": "-1390838108",
    "frmtrm_add_amount": "-1390838108",
    "ord": "9",
    "currency": "KRW"
  },
  {
    "rcept_no": "20220516000629",
    "reprt_code": "11013",
    "bsns_year": "2022",
    "corp_code": "00493510",
    "sj_div": "CIS",
    "sj_nm": "포괄손익계산서",
    "account_id": "ifrs-full_IncomeTaxExpenseContinuingOperations",
    "account_nm": "법인세비용",
    "account_detail": "-",
    "thstrm_nm": "제 23 기 1분기",
    "thstrm_amount": "470544110",
    "thstrm_add_amount": "470544110",
    "frmtrm_q_nm": "제 22 기 1분기",
    "frmtrm_q_amount": "-186104331",
    "frmtrm_add_amount": "-186104331",
    "ord": "10",
    "currency": "KRW"
  },
  {
    "rcept_no": "20220516000629",
    "reprt_code": "11013",
    "bsns_year": "2022",
    "corp_code": "00493510",
    "sj_div": "CIS",
    "sj_nm": "포괄손익계산서",
    "account_id": "ifrs-full_ProfitLoss",
    "account_nm": "당기순이익(손실)",
    "account_detail": "-",
    "thstrm_nm": "제 23 기 1분기",
    "thstrm_amount": "7405506289",
    "thstrm_add_amount": "7405506289",
    "frmtrm_q_nm": "제 22 기 1분기",
    "frmtrm_q_amount": "-1204733777",
    "frmtrm_add_amount": "-1204733777",
    "ord": "11",
    "currency": "KRW"
  },
  {
    "rcept_no": "20220516000629",
    "reprt_code": "11013",
    "bsns_year": "2022",
    "corp_code": "00493510",
    "sj_div": "CIS",
    "sj_nm": "포괄손익계산서",
    "account_id": "ifrs-full_OtherComprehensiveIncome",
    "account_nm": "기타포괄손익",
    "account_detail": "-",
    "thstrm_nm": "제 23 기 1분기",
    "thstrm_amount": "-120150307",
    "thstrm_add_amount": "-120150307",
    "frmtrm_q_nm": "제 22 기 1분기",
    "frmtrm_q_amount": "218428951",
    "frmtrm_add_amount": "218428951",
    "ord": "12",
    "currency": "KRW"
  },
  {
    "rcept_no": "20220516000629",
    "reprt_code": "11013",
    "bsns_year": "2022",
    "corp_code": "00493510",
    "sj_div": "CIS",
    "sj_nm": "포괄손익계산서",
    "account_id": "dart_OtherComprehensiveIncomeThatWillNotBeReclassifiedToProfitOrLossNetOfTax",
    "account_nm": "후속적으로 당기손익으로 재분류되지 않는항목(세후기타포괄손익)",
    "account_detail": "-",
    "thstrm_nm": "제 23 기 1분기",
    "thstrm_amount": "",
    "thstrm_add_amount": "",
    "frmtrm_q_nm": "제 22 기 1분기",
    "frmtrm_q_amount": "25758866",
    "frmtrm_add_amount": "25758866",
    "ord": "13",
    "currency": "KRW"
  },
  {
    "rcept_no": "20220516000629",
    "reprt_code": "11013",
    "bsns_year": "2022",
    "corp_code": "00493510",
    "sj_div": "CIS",
    "sj_nm": "포괄손익계산서",
    "account_id": "dart_OtherComprehensiveIncomeNetOfTaxGainsLossesOnRemeasurementsOfDefinedBenefitPlans",
    "account_nm": "보험수리적손익",
    "account_detail": "-",
    "thstrm_nm": "제 23 기 1분기",
    "thstrm_amount": "",
    "thstrm_add_amount": "",
    "frmtrm_q_nm": "제 22 기 1분기",
    "frmtrm_q_amount": "25758866",
    "frmtrm_add_amount": "25758866",
    "ord": "14",
    "currency": "KRW"
  },
  {
    "rcept_no": "20220516000629",
    "reprt_code": "11013",
    "bsns_year": "2022",
    "corp_code": "00493510",
    "sj_div": "CIS",
    "sj_nm": "포괄손익계산서",
    "account_id": "dart_OtherComprehensiveIncomeThatWillBeReclassifiedToProfitOrLossNetOfTax",
    "account_nm": "후속적으로 당기손익으로 재분류될 수 있는 항목(세후기타포괄손익)",
    "account_detail": "-",
    "thstrm_nm": "제 23 기 1분기",
    "thstrm_amount": "",
    "thstrm_add_amount": "",
    "frmtrm_q_nm": "제 22 기 1분기",
    "frmtrm_q_amount": "192670085",
    "frmtrm_add_amount": "192670085",
    "ord": "15",
    "currency": "KRW"
  },
  {
    "rcept_no": "20220516000629",
    "reprt_code": "11013",
    "bsns_year": "2022",
    "corp_code": "00493510",
    "sj_div": "CIS",
    "sj_nm": "포괄손익계산서",
    "account_id": "ifrs-full_GainsLossesOnExchangeDifferencesOnTranslationNetOfTax",
    "account_nm": "해외사업장환산외환차이",
    "account_detail": "-",
    "thstrm_nm": "제 23 기 1분기",
    "thstrm_amount": "-120150307",
    "thstrm_add_amount": "-120150307",
    "frmtrm_q_nm": "제 22 기 1분기",
    "frmtrm_q_amount": "192670085",
    "frmtrm_add_amount": "192670085",
    "ord": "16",
    "currency": "KRW"
  },
  {
    "rcept_no": "20220516000629",
    "reprt_code": "11013",
    "bsns_year": "2022",
    "corp_code": "00493510",
    "sj_div": "CIS",
    "sj_nm": "포괄손익계산서",
    "account_id": "ifrs-full_ComprehensiveIncome",
    "account_nm": "총포괄손익",
    "account_detail": "-",
    "thstrm_nm": "제 23 기 1분기",
    "thstrm_amount": "7285355982",
    "thstrm_add_amount": "7285355982",
    "frmtrm_q_nm": "제 22 기 1분기",
    "frmtrm_q_amount": "-986304826",
    "frmtrm_add_amount": "-986304826",
    "ord": "17",
    "currency": "KRW"
  },
  {
    "rcept_no": "20220516000629",
    "reprt_code": "11013",
    "bsns_year": "2022",
    "corp_code": "00493510",
    "sj_div": "CIS",
    "sj_nm": "포괄손익계산서",
    "account_id": "ifrs-full_ProfitLossAttributableToOwnersOfParent",
    "account_nm": "지배기업순이익 지분",
    "account_detail": "-",
    "thstrm_nm": "제 23 기 1분기",
    "thstrm_amount": "7376537612",
    "thstrm_add_amount": "7376537612",
    "frmtrm_q_nm": "제 22 기 1분기",
    "frmtrm_q_amount": "-1132650760",
    "frmtrm_add_amount": "-1132650760",
    "ord": "19",
    "currency": "KRW"
  },
  {
    "rcept_no": "20220516000629",
    "reprt_code": "11013",
    "bsns_year": "2022",
    "corp_code": "00493510",
    "sj_div": "CIS",
    "sj_nm": "포괄손익계산서",
    "account_id": "ifrs-full_ProfitLossAttributableToNoncontrollingInterests",
    "account_nm": "비지배기업순이익 지분",
    "account_detail": "-",
    "thstrm_nm": "제 23 기 1분기",
    "thstrm_amount": "28968677",
    "thstrm_add_amount": "28968677",
    "frmtrm_q_nm": "제 22 기 1분기",
    "frmtrm_q_amount": "-72083017",
    "frmtrm_add_amount": "-72083017",
    "ord": "20",
    "currency": "KRW"
  },
  {
    "rcept_no": "20220516000629",
    "reprt_code": "11013",
    "bsns_year": "2022",
    "corp_code": "00493510",
    "sj_div": "CIS",
    "sj_nm": "포괄손익계산서",
    "account_id": "ifrs-full_ComprehensiveIncomeAttributableToOwnersOfParent",
    "account_nm": "지배기업포괄순이익 지분",
    "account_detail": "-",
    "thstrm_nm": "제 23 기 1분기",
    "thstrm_amount": "7256387305",
    "thstrm_add_amount": "7256387305",
    "frmtrm_q_nm": "제 22 기 1분기",
    "frmtrm_q_amount": "-930999887",
    "frmtrm_add_amount": "-930999887",
    "ord": "22",
    "currency": "KRW"
  },
  {
    "rcept_no": "20220516000629",
    "reprt_code": "11013",
    "bsns_year": "2022",
    "corp_code": "00493510",
    "sj_div": "CIS",
    "sj_nm": "포괄손익계산서",
    "account_id": "ifrs-full_ComprehensiveIncomeAttributableToNoncontrollingInterests",
    "account_nm": "비지배기업포괄순이익 지분",
    "account_detail": "-",
    "thstrm_nm": "제 23 기 1분기",
    "thstrm_amount": "28968677",
    "thstrm_add_amount": "28968677",
    "frmtrm_q_nm": "제 22 기 1분기",
    "frmtrm_q_amount": "-55304939",
    "frmtrm_add_amount": "-55304939",
    "ord": "23",
    "currency": "KRW"
  },
  {
    "rcept_no": "20220516000629",
    "reprt_code": "11013",
    "bsns_year": "2022",
    "corp_code": "00493510",
    "sj_div": "CIS",
    "sj_nm": "포괄손익계산서",
    "account_id": "ifrs-full_BasicEarningsLossPerShare",
    "account_nm": "기본주당이익(손실)",
    "account_detail": "-",
    "thstrm_nm": "제 23 기 1분기",
    "thstrm_amount": "305",
    "thstrm_add_amount": "305",
    "frmtrm_q_nm": "제 22 기 1분기",
    "frmtrm_q_amount": "-52",
    "frmtrm_add_amount": "-52",
    "ord": "25",
    "currency": "KRW"
  },
  {
    "rcept_no": "20220516000629",
    "reprt_code": "11013",
    "bsns_year": "2022",
    "corp_code": "00493510",
    "sj_div": "CIS",
    "sj_nm": "포괄손익계산서",
    "account_id": "ifrs-full_DilutedEarningsLossPerShare",
    "account_nm": "희석주당이익(손실)",
    "account_detail": "-",
    "thstrm_nm": "제 23 기 1분기",
    "thstrm_amount": "304",
    "thstrm_add_amount": "304",
    "frmtrm_q_nm": "제 22 기 1분기",
    "frmtrm_q_amount": "-52",
    "frmtrm_add_amount": "-52",
    "ord": "26",
    "currency": "KRW"
  },
  {
    "rcept_no": "20220516000629",
    "reprt_code": "11013",
    "bsns_year": "2022",
    "corp_code": "00493510",
    "sj_div": "CF",
    "sj_nm": "현금흐름표",
    "account_id": "ifrs-full_CashFlowsFromUsedInOperatingActivities",
    "account_nm": "영업활동현금흐름",
    "account_detail": "-",
    "thstrm_nm": "제 23 기 1분기",
    "thstrm_amount": "6049361634",
    "frmtrm_q_nm": "제 22 기 1분기",
    "frmtrm_q_amount": "2495064825",
    "ord": "0",
    "currency": "KRW"
  },
  {
    "rcept_no": "20220516000629",
    "reprt_code": "11013",
    "bsns_year": "2022",
    "corp_code": "00493510",
    "sj_div": "CF",
    "sj_nm": "현금흐름표",
    "account_id": "dart_ProfitLossForStatementOfCashFlows",
    "account_nm": "당기순이익(손실)",
    "account_detail": "-",
    "thstrm_nm": "제 23 기 1분기",
    "thstrm_amount": "7405506289",
    "frmtrm_q_nm": "제 22 기 1분기",
    "frmtrm_q_amount": "-1204733777",
    "ord": "1",
    "currency": "KRW"
  },
  {
    "rcept_no": "20220516000629",
    "reprt_code": "11013",
    "bsns_year": "2022",
    "corp_code": "00493510",
    "sj_div": "CF",
    "sj_nm": "현금흐름표",
    "account_id": "ifrs-full_AdjustmentsForReconcileProfitLoss",
    "account_nm": "당기순이익조정을 위한 가감",
    "account_detail": "-",
    "thstrm_nm": "제 23 기 1분기",
    "thstrm_amount": "3869872918",
    "frmtrm_q_nm": "제 22 기 1분기",
    "frmtrm_q_amount": "2235193104",
    "ord": "2",
    "currency": "KRW"
  },
  {
    "rcept_no": "20220516000629",
    "reprt_code": "11013",
    "bsns_year": "2022",
    "corp_code": "00493510",
    "sj_div": "CF",
    "sj_nm": "현금흐름표",
    "account_id": "ifrs-full_AdjustmentsForIncomeTaxExpense",
    "account_nm": "법인세비용",
    "account_detail": "-",
    "thstrm_nm": "제 23 기 1분기",
    "thstrm_amount": "470544110",
    "frmtrm_q_nm": "제 22 기 1분기",
    "frmtrm_q_amount": "-186104331",
    "ord": "3",
    "currency": "KRW"
  },
  {
    "rcept_no": "20220516000629",
    "reprt_code": "11013",
    "bsns_year": "2022",
    "corp_code": "00493510",
    "sj_div": "CF",
    "sj_nm": "현금흐름표",
    "account_id": "dart_AdjustmentsForProvisionForSeveranceIndemnities",
    "account_nm": "퇴직급여",
    "account_detail": "-",
    "thstrm_nm": "제 23 기 1분기",
    "thstrm_amount": "730274100",
    "frmtrm_q_nm": "제 22 기 1분기",
    "frmtrm_q_amount": "703928528",
    "ord": "4",
    "currency": "KRW"
  },
  {
    "rcept_no": "20220516000629",
    "reprt_code": "11013",
    "bsns_year": "2022",
    "corp_code": "00493510",
    "sj_div": "CF",
    "sj_nm": "현금흐름표",
    "account_id": "dart_AdjustmentsForDepreciationExpense",
    "account_nm": "감가상각비",
    "account_detail": "-",
    "thstrm_nm": "제 23 기 1분기",
    "thstrm_amount": "2568189089",
    "frmtrm_q_nm": "제 22 기 1분기",
    "frmtrm_q_amount": "2032685002",
    "ord": "5",
    "currency": "KRW"
  },
  {
    "rcept_no": "20220516000629",
    "reprt_code": "11013",
    "bsns_year": "2022",
    "corp_code": "00493510",
    "sj_div": "CF",
    "sj_nm": "현금흐름표",
    "account_id": "dart_AdjustmentsForAmortisationExpense",
    "account_nm": "무형자산상각비",
    "account_detail": "-",
    "thstrm_nm": "제 23 기 1분기",
    "thstrm_amount": "75952041",
    "frmtrm_q_nm": "제 22 기 1분기",
    "frmtrm_q_amount": "81583526",
    "ord": "6",
    "currency": "KRW"
  },
  {
    "rcept_no": "20220516000629",
    "reprt_code": "11013",
    "bsns_year": "2022",
    "corp_code": "00493510",
    "sj_div": "CF",
    "sj_nm": "현금흐름표",
    "account_id": "dart_AdjustmentsForBadDebtExpenses",
    "account_nm": "대손상각비",
    "account_detail": "-",
    "thstrm_nm": "제 23 기 1분기",
    "thstrm_amount": "36354155",
    "frmtrm_q_nm": "제 22 기 1분기",
    "frmtrm_q_amount": "-30339675",
    "ord": "7",
    "currency": "KRW"
  },
  {
    "rcept_no": "20220516000629",
    "reprt_code": "11013",
    "bsns_year": "2022",
    "corp_code": "00493510",
    "sj_div": "CF",
    "sj_nm": "현금흐름표",
    "account_id": "dart_AdjustmentsForLossesOnForeignExchangeTranslations",
    "account_nm": "외화환산손실",
    "account_detail": "-",
    "thstrm_nm": "제 23 기 1분기",
    "thstrm_amount": "93404664",
    "frmtrm_q_nm": "제 22 기 1분기",
    "frmtrm_q_amount": "216496485",
    "ord": "8",
    "currency": "KRW"
  },
  {
    "rcept_no": "20220516000629",
    "reprt_code": "11013",
    "bsns_year": "2022",
    "corp_code": "00493510",
    "sj_div": "CF",
    "sj_nm": "현금흐름표",
    "account_id": "dart_AdjustmentsForInterestExpenses",
    "account_nm": "이자비용",
    "account_detail": "-",
    "thstrm_nm": "제 23 기 1분기",
    "thstrm_amount": "566326764",
    "frmtrm_q_nm": "제 22 기 1분기",
    "frmtrm_q_amount": "259182846",
    "ord": "9",
    "currency": "KRW"
  },
  {
    "rcept_no": "20220516000629",
    "reprt_code": "11013",
    "bsns_year": "2022",
    "corp_code": "00493510",
    "sj_div": "CF",
    "sj_nm": "현금흐름표",
    "account_id": "dart_AdjustmentsForShareBasedPayment",
    "account_nm": "주식보상비용(환입)",
    "account_detail": "-",
    "thstrm_nm": "제 23 기 1분기",
    "thstrm_amount": "7978069",
    "frmtrm_q_nm": "제 22 기 1분기",
    "ord": "10",
    "currency": "KRW"
  },
  {
    "rcept_no": "20220516000629",
    "reprt_code": "11013",
    "bsns_year": "2022",
    "corp_code": "00493510",
    "sj_div": "CF",
    "sj_nm": "현금흐름표",
    "account_id": "dart_AdjustmentsForGainOnForeignExchangeTranslations",
    "account_nm": "외화환산이익",
    "account_detail": "-",
    "thstrm_nm": "제 23 기 1분기",
    "thstrm_amount": "614968230",
    "frmtrm_q_nm": "제 22 기 1분기",
    "frmtrm_q_amount": "511529945",
    "ord": "11",
    "currency": "KRW"
  },
  {
    "rcept_no": "20220516000629",
    "reprt_code": "11013",
    "bsns_year": "2022",
    "corp_code": "00493510",
    "sj_div": "CF",
    "sj_nm": "현금흐름표",
    "account_id": "dart_AdjustmentsForInterestIncome",
    "account_nm": "이자수익",
    "account_detail": "-",
    "thstrm_nm": "제 23 기 1분기",
    "thstrm_amount": "64181844",
    "frmtrm_q_nm": "제 22 기 1분기",
    "frmtrm_q_amount": "37409161",
    "ord": "12",
    "currency": "KRW"
  },
  {
    "rcept_no": "20220516000629",
    "reprt_code": "11013",
    "bsns_year": "2022",
    "corp_code": "00493510",
    "sj_div": "CF",
    "sj_nm": "현금흐름표",
    "account_id": "dart_AdjustmentsForMiscellaneousIncome",
    "account_nm": "잡이익",
    "account_detail": "-",
    "thstrm_nm": "제 23 기 1분기",
    "thstrm_amount": "",
    "frmtrm_q_nm": "제 22 기 1분기",
    "frmtrm_q_amount": "293300171",
    "ord": "13",
    "currency": "KRW"
  },
  {
    "rcept_no": "20220516000629",
    "reprt_code": "11013",
    "bsns_year": "2022",
    "corp_code": "00493510",
    "sj_div": "CF",
    "sj_nm": "현금흐름표",
    "account_id": "dart_AdjustmentsForAssetsLiabilitiesOfOperatingActivities",
    "account_nm": "영업활동으로인한자산ㆍ부채의변동",
    "account_detail": "-",
    "thstrm_nm": "제 23 기 1분기",
    "thstrm_amount": "-4880055561",
    "frmtrm_q_nm": "제 22 기 1분기",
    "frmtrm_q_amount": "1756148464",
    "ord": "14",
    "currency": "KRW"
  },
  {
    "rcept_no": "20220516000629",
    "reprt_code": "11013",
    "bsns_year": "2022",
    "corp_code": "00493510",
    "sj_div": "CF",
    "sj_nm": "현금흐름표",
    "account_id": "ifrs-full_AdjustmentsForDecreaseIncreaseInTradeAccountReceivable",
    "account_nm": "매출채권의 증가",
    "account_detail": "-",
    "thstrm_nm": "제 23 기 1분기",
    "thstrm_amount": "269552722",
    "frmtrm_q_nm": "제 22 기 1분기",
    "frmtrm_q_amount": "3265841474",
    "ord": "15",
    "currency": "KRW"
  },
  {
    "rcept_no": "20220516000629",
    "reprt_code": "11013",
    "bsns_year": "2022",
    "corp_code": "00493510",
    "sj_div": "CF",
    "sj_nm": "현금흐름표",
    "account_id": "dart_AdjustmentsForDecreaseincreaseInOtherReceivables",
    "account_nm": "기타수취채권의 감소",
    "account_detail": "-",
    "thstrm_nm": "제 23 기 1분기",
    "thstrm_amount": "-636160006",
    "frmtrm_q_nm": "제 22 기 1분기",
    "frmtrm_q_amount": "742449074",
    "ord": "16",
    "currency": "KRW"
  },
  {
    "rcept_no": "20220516000629",
    "reprt_code": "11013",
    "bsns_year": "2022",
    "corp_code": "00493510",
    "sj_div": "CF",
    "sj_nm": "현금흐름표",
    "account_id": "dart_AdjustmentsForDecreaseIncreaseInOtherCurrentAssets",
    "account_nm": "기타유동자산의 감소",
    "account_detail": "-",
    "thstrm_nm": "제 23 기 1분기",
    "thstrm_amount": "-1526990007",
    "frmtrm_q_nm": "제 22 기 1분기",
    "frmtrm_q_amount": "68677602",
    "ord": "17",
    "currency": "KRW"
  },
  {
    "rcept_no": "20220516000629",
    "reprt_code": "11013",
    "bsns_year": "2022",
    "corp_code": "00493510",
    "sj_div": "CF",
    "sj_nm": "현금흐름표",
    "account_id": "ifrs-full_AdjustmentsForDecreaseIncreaseInInventories",
    "account_nm": "재고자산의 감소",
    "account_detail": "-",
    "thstrm_nm": "제 23 기 1분기",
    "thstrm_amount": "-493197835",
    "frmtrm_q_nm": "제 22 기 1분기",
    "frmtrm_q_amount": "1692502645",
    "ord": "18",
    "currency": "KRW"
  },
  {
    "rcept_no": "20220516000629",
    "reprt_code": "11013",
    "bsns_year": "2022",
    "corp_code": "00493510",
    "sj_div": "CF",
    "sj_nm": "현금흐름표",
    "account_id": "ifrs-full_AdjustmentsForIncreaseDecreaseInTradeAccountPayable",
    "account_nm": "매입채무의 증가",
    "account_detail": "-",
    "thstrm_nm": "제 23 기 1분기",
    "thstrm_amount": "-2255816894",
    "frmtrm_q_nm": "제 22 기 1분기",
    "frmtrm_q_amount": "-3095397052",
    "ord": "19",
    "currency": "KRW"
  },
  {
    "rcept_no": "20220516000629",
    "reprt_code": "11013",
    "bsns_year": "2022",
    "corp_code": "00493510",
    "sj_div": "CF",
    "sj_nm": "현금흐름표",
    "account_id": "dart_AdjustmentsForIncreasedecreaseInTradeAndOtherPayables",
    "account_nm": "기타지급채무의 증가(감소)",
    "account_detail": "-",
    "thstrm_nm": "제 23 기 1분기",
    "thstrm_amount": "-150618025",
    "frmtrm_q_nm": "제 22 기 1분기",
    "frmtrm_q_amount": "-327659121",
    "ord": "20",
    "currency": "KRW"
  },
  {
    "rcept_no": "20220516000629",
    "reprt_code": "11013",
    "bsns_year": "2022",
    "corp_code": "00493510",
    "sj_div": "CF",
    "sj_nm": "현금흐름표",
    "account_id": "dart_AdjustmentsForIncreaseDecreaseInOtherCurrentLiabilities",
    "account_nm": "기타유동부채의 증가(감소)",
    "account_detail": "-",
    "thstrm_nm": "제 23 기 1분기",
    "thstrm_amount": "71972521",
    "frmtrm_q_nm": "제 22 기 1분기",
    "frmtrm_q_amount": "16591212",
    "ord": "21",
    "currency": "KRW"
  },
  {
    "rcept_no": "20220516000629",
    "reprt_code": "11013",
    "bsns_year": "2022",
    "corp_code": "00493510",
    "sj_div": "CF",
    "sj_nm": "현금흐름표",
    "account_id": "dart_AdjustmentsForIncreaseDecreaseInOtherNonCurrentLiabilities",
    "account_nm": "기타비유동부채의 증가(감소)",
    "account_detail": "-",
    "thstrm_nm": "제 23 기 1분기",
    "thstrm_amount": "78847845",
    "frmtrm_q_nm": "제 22 기 1분기",
    "ord": "22",
    "currency": "KRW"
  },
  {
    "rcept_no": "20220516000629",
    "reprt_code": "11013",
    "bsns_year": "2022",
    "corp_code": "00493510",
    "sj_div": "CF",
    "sj_nm": "현금흐름표",
    "account_id": "dart_AdjustmentsForIncreasedecreaseInPostemploymentBenefitObligations",
    "account_nm": "퇴직금의 지급",
    "account_detail": "-",
    "thstrm_nm": "제 23 기 1분기",
    "thstrm_amount": "-237645882",
    "frmtrm_q_nm": "제 22 기 1분기",
    "frmtrm_q_amount": "-606857370",
    "ord": "23",
    "currency": "KRW"
  },
  {
    "rcept_no": "20220516000629",
    "reprt_code": "11013",
    "bsns_year": "2022",
    "corp_code": "00493510",
    "sj_div": "CF",
    "sj_nm": "현금흐름표",
    "account_id": "ifrs-full_InterestReceivedClassifiedAsOperatingActivities",
    "account_nm": "이자수취(영업)",
    "account_detail": "-",
    "thstrm_nm": "제 23 기 1분기",
    "thstrm_amount": "33930742",
    "frmtrm_q_nm": "제 22 기 1분기",
    "frmtrm_q_amount": "19028859",
    "ord": "24",
    "currency": "KRW"
  },
  {
    "rcept_no": "20220516000629",
    "reprt_code": "11013",
    "bsns_year": "2022",
    "corp_code": "00493510",
    "sj_div": "CF",
    "sj_nm": "현금흐름표",
    "account_id": "ifrs-full_InterestPaidClassifiedAsOperatingActivities",
    "account_nm": "이자지급(영업)",
    "account_detail": "-",
    "thstrm_nm": "제 23 기 1분기",
    "thstrm_amount": "371697274",
    "frmtrm_q_nm": "제 22 기 1분기",
    "frmtrm_q_amount": "313376595",
    "ord": "25",
    "currency": "KRW"
  },
  {
    "rcept_no": "20220516000629",
    "reprt_code": "11013",
    "bsns_year": "2022",
    "corp_code": "00493510",
    "sj_div": "CF",
    "sj_nm": "현금흐름표",
    "account_id": "ifrs-full_IncomeTaxesPaidRefundClassifiedAsOperatingActivities",
    "account_nm": "법인세납부(환급)",
    "account_detail": "-",
    "thstrm_nm": "제 23 기 1분기",
    "thstrm_amount": "8195480",
    "frmtrm_q_nm": "제 22 기 1분기",
    "frmtrm_q_amount": "-2804770",
    "ord": "26",
    "currency": "KRW"
  },
  {
    "rcept_no": "20220516000629",
    "reprt_code": "11013",
    "bsns_year": "2022",
    "corp_code": "00493510",
    "sj_div": "CF",
    "sj_nm": "현금흐름표",
    "account_id": "ifrs-full_CashFlowsFromUsedInInvestingActivities",
    "account_nm": "투자활동현금흐름",
    "account_detail": "-",
    "thstrm_nm": "제 23 기 1분기",
    "thstrm_amount": "-1294222850",
    "frmtrm_q_nm": "제 22 기 1분기",
    "frmtrm_q_amount": "-1660317429",
    "ord": "27",
    "currency": "KRW"
  },
  {
    "rcept_no": "20220516000629",
    "reprt_code": "11013",
    "bsns_year": "2022",
    "corp_code": "00493510",
    "sj_div": "CF",
    "sj_nm": "현금흐름표",
    "account_id": "dart_ProceedsFromSalesOfShortTermFinancialInstruments",
    "account_nm": "단기금융상품의 감소",
    "account_detail": "-",
    "thstrm_nm": "제 23 기 1분기",
    "thstrm_amount": "",
    "frmtrm_q_nm": "제 22 기 1분기",
    "frmtrm_q_amount": "600000000",
    "ord": "28",
    "currency": "KRW"
  },
  {
    "rcept_no": "20220516000629",
    "reprt_code": "11013",
    "bsns_year": "2022",
    "corp_code": "00493510",
    "sj_div": "CF",
    "sj_nm": "현금흐름표",
    "account_id": "dart_PurchaseOfShortTermFinancialInstruments",
    "account_nm": "단기금융상품의 취득",
    "account_detail": "-",
    "thstrm_nm": "제 23 기 1분기",
    "thstrm_amount": "120000000",
    "frmtrm_q_nm": "제 22 기 1분기",
    "frmtrm_q_amount": "100000000",
    "ord": "29",
    "currency": "KRW"
  },
  {
    "rcept_no": "20220516000629",
    "reprt_code": "11013",
    "bsns_year": "2022",
    "corp_code": "00493510",
    "sj_div": "CF",
    "sj_nm": "현금흐름표",
    "account_id": "dart_PurchaseOfLongTermFinancialInstruments",
    "account_nm": "장기금융상품의 증가",
    "account_detail": "-",
    "thstrm_nm": "제 23 기 1분기",
    "thstrm_amount": "180000000",
    "frmtrm_q_nm": "제 22 기 1분기",
    "frmtrm_q_amount": "123021387",
    "ord": "30",
    "currency": "KRW"
  },
  {
    "rcept_no": "20220516000629",
    "reprt_code": "11013",
    "bsns_year": "2022",
    "corp_code": "00493510",
    "sj_div": "CF",
    "sj_nm": "현금흐름표",
    "account_id": "ifrs-full_PurchaseOfPropertyPlantAndEquipmentClassifiedAsInvestingActivities",
    "account_nm": "유형자산의 취득",
    "account_detail": "-",
    "thstrm_nm": "제 23 기 1분기",
    "thstrm_amount": "994222850",
    "frmtrm_q_nm": "제 22 기 1분기",
    "frmtrm_q_amount": "2032171042",
    "ord": "31",
    "currency": "KRW"
  },
  {
    "rcept_no": "20220516000629",
    "reprt_code": "11013",
    "bsns_year": "2022",
    "corp_code": "00493510",
    "sj_div": "CF",
    "sj_nm": "현금흐름표",
    "account_id": "ifrs-full_PurchaseOfIntangibleAssetsClassifiedAsInvestingActivities",
    "account_nm": "무형자산의 취득",
    "account_detail": "-",
    "thstrm_nm": "제 23 기 1분기",
    "thstrm_amount": "",
    "frmtrm_q_nm": "제 22 기 1분기",
    "frmtrm_q_amount": "5125000",
    "ord": "32",
    "currency": "KRW"
  },
  {
    "rcept_no": "20220516000629",
    "reprt_code": "11013",
    "bsns_year": "2022",
    "corp_code": "00493510",
    "sj_div": "CF",
    "sj_nm": "현금흐름표",
    "account_id": "ifrs-full_CashFlowsFromUsedInFinancingActivities",
    "account_nm": "재무활동현금흐름",
    "account_detail": "-",
    "thstrm_nm": "제 23 기 1분기",
    "thstrm_amount": "-3954866760",
    "frmtrm_q_nm": "제 22 기 1분기",
    "frmtrm_q_amount": "-1506211391",
    "ord": "33",
    "currency": "KRW"
  },
  {
    "rcept_no": "20220516000629",
    "reprt_code": "11013",
    "bsns_year": "2022",
    "corp_code": "00493510",
    "sj_div": "CF",
    "sj_nm": "현금흐름표",
    "account_id": "dart_ProceedsFromShortTermBorrowings",
    "account_nm": "단기차입금의 차입",
    "account_detail": "-",
    "thstrm_nm": "제 23 기 1분기",
    "thstrm_amount": "18711375954",
    "frmtrm_q_nm": "제 22 기 1분기",
    "frmtrm_q_amount": "18066536406",
    "ord": "34",
    "currency": "KRW"
  },
  {
    "rcept_no": "20220516000629",
    "reprt_code": "11013",
    "bsns_year": "2022",
    "corp_code": "00493510",
    "sj_div": "CF",
    "sj_nm": "현금흐름표",
    "account_id": "dart_RepaymentsOfShortTermBorrowings",
    "account_nm": "단기차입금의 상환",
    "account_detail": "-",
    "thstrm_nm": "제 23 기 1분기",
    "thstrm_amount": "18955350714",
    "frmtrm_q_nm": "제 22 기 1분기",
    "frmtrm_q_amount": "16690807800",
    "ord": "35",
    "currency": "KRW"
  },
  {
    "rcept_no": "20220516000629",
    "reprt_code": "11013",
    "bsns_year": "2022",
    "corp_code": "00493510",
    "sj_div": "CF",
    "sj_nm": "현금흐름표",
    "account_id": "ifrs-full_RepaymentsOfBorrowingsClassifiedAsFinancingActivities",
    "account_nm": "기타금융부채의 상환",
    "account_detail": "-",
    "thstrm_nm": "제 23 기 1분기",
    "thstrm_amount": "3710892000",
    "frmtrm_q_nm": "제 22 기 1분기",
    "frmtrm_q_amount": "2073639997",
    "ord": "36",
    "currency": "KRW"
  },
  {
    "rcept_no": "20220516000629",
    "reprt_code": "11013",
    "bsns_year": "2022",
    "corp_code": "00493510",
    "sj_div": "CF",
    "sj_nm": "현금흐름표",
    "account_id": "dart_RepaymentsOfLongTermBorrowings",
    "account_nm": "장기차입금의 상환",
    "account_detail": "-",
    "thstrm_nm": "제 23 기 1분기",
    "thstrm_amount": "",
    "frmtrm_q_nm": "제 22 기 1분기",
    "frmtrm_q_amount": "808300000",
    "ord": "37",
    "currency": "KRW"
  },
  {
    "rcept_no": "20220516000629",
    "reprt_code": "11013",
    "bsns_year": "2022",
    "corp_code": "00493510",
    "sj_div": "CF",
    "sj_nm": "현금흐름표",
    "account_id": "ifrs-full_IncreaseDecreaseInCashAndCashEquivalentsBeforeEffectOfExchangeRateChanges",
    "account_nm": "환율변동효과 반영전 현금및현금성자산의 순증가(감소)",
    "account_detail": "-",
    "thstrm_nm": "제 23 기 1분기",
    "thstrm_amount": "800272024",
    "frmtrm_q_nm": "제 22 기 1분기",
    "frmtrm_q_amount": "-671463995",
    "ord": "38",
    "currency": "KRW"
  },
  {
    "rcept_no": "20220516000629",
    "reprt_code": "11013",
    "bsns_year": "2022",
    "corp_code": "00493510",
    "sj_div": "CF",
    "sj_nm": "현금흐름표",
    "account_id": "ifrs-full_EffectOfExchangeRateChangesOnCashAndCashEquivalents",
    "account_nm": "현금및현금성자산에 대한 환율변동효과",
    "account_detail": "-",
    "thstrm_nm": "제 23 기 1분기",
    "thstrm_amount": "-27404364",
    "frmtrm_q_nm": "제 22 기 1분기",
    "frmtrm_q_amount": "51997628",
    "ord": "39",
    "currency": "KRW"
  },
  {
    "rcept_no": "20220516000629",
    "reprt_code": "11013",
    "bsns_year": "2022",
    "corp_code": "00493510",
    "sj_div": "CF",
    "sj_nm": "현금흐름표",
    "account_id": "ifrs-full_IncreaseDecreaseInCashAndCashEquivalents",
    "account_nm": "현금및현금성자산의순증가(감소)",
    "account_detail": "-",
    "thstrm_nm": "제 23 기 1분기",
    "thstrm_amount": "772867660",
    "frmtrm_q_nm": "제 22 기 1분기",
    "frmtrm_q_amount": "-619466367",
    "ord": "40",
    "currency": "KRW"
  },
  {
    "rcept_no": "20220516000629",
    "reprt_code": "11013",
    "bsns_year": "2022",
    "corp_code": "00493510",
    "sj_div": "CF",
    "sj_nm": "현금흐름표",
    "account_id": "dart_CashAndCashEquivalentsAtBeginningOfPeriodCf",
    "account_nm": "기초현금및현금성자산",
    "account_detail": "-",
    "thstrm_nm": "제 23 기 1분기",
    "thstrm_amount": "1280972255",
    "frmtrm_q_nm": "제 22 기 1분기",
    "frmtrm_q_amount": "5589423831",
    "ord": "41",
    "currency": "KRW"
  },
  {
    "rcept_no": "20220516000629",
    "reprt_code": "11013",
    "bsns_year": "2022",
    "corp_code": "00493510",
    "sj_div": "CF",
    "sj_nm": "현금흐름표",
    "account_id": "dart_CashAndCashEquivalentsAtEndOfPeriodCf",
    "account_nm": "기말현금및현금성자산",
    "account_detail": "-",
    "thstrm_nm": "제 23 기 1분기",
    "thstrm_amount": "2053839915",
    "frmtrm_q_nm": "제 22 기 1분기",
    "frmtrm_q_amount": "4969957464",
    "ord": "42",
    "currency": "KRW"
  },
  {
    "rcept_no": "20220516000629",
    "reprt_code": "11013",
    "bsns_year": "2022",
    "corp_code": "00493510",
    "sj_div": "SCE",
    "sj_nm": "자본변동표",
    "account_id": "dart_EquityAtBeginningOfPeriod",
    "account_nm": "기초자본",
    "account_detail": "자본 [member]|지배기업의 소유주에게 귀속되는 자본 [member]",
    "thstrm_nm": "제 23 기 1분기",
    "thstrm_amount": "51020746524",
    "frmtrm_q_nm": "제 22 기 1분기",
    "frmtrm_q_amount": "38717040612",
    "ord": "1",
    "currency": "KRW"
  },
  {
    "rcept_no": "20220516000629",
    "reprt_code": "11013",
    "bsns_year": "2022",
    "corp_code": "00493510",
    "sj_div": "SCE",
    "sj_nm": "자본변동표",
    "account_id": "dart_EquityAtBeginningOfPeriod",
    "account_nm": "기초자본",
    "account_detail": "자본 [member]|지배기업의 소유주에게 귀속되는 자본 [member]|자본잉여금 [member]",
    "thstrm_nm": "제 23 기 1분기",
    "thstrm_amount": "20546908407",
    "frmtrm_q_nm": "제 22 기 1분기",
    "frmtrm_q_amount": "15187578456",
    "ord": "1",
    "currency": "KRW"
  },
  {
    "rcept_no": "20220516000629",
    "reprt_code": "11013",
    "bsns_year": "2022",
    "corp_code": "00493510",
    "sj_div": "SCE",
    "sj_nm": "자본변동표",
    "account_id": "dart_EquityAtBeginningOfPeriod",
    "account_nm": "기초자본",
    "account_detail": "자본 [member]|지배기업의 소유주에게 귀속되는 자본 [member]|자본금 [member]",
    "thstrm_nm": "제 23 기 1분기",
    "thstrm_amount": "12104876500",
    "frmtrm_q_nm": "제 22 기 1분기",
    "frmtrm_q_amount": "10884796057",
    "ord": "1",
    "currency": "KRW"
  },
  {
    "rcept_no": "20220516000629",
    "reprt_code": "11013",
    "bsns_year": "2022",
    "corp_code": "00493510",
    "sj_div": "SCE",
    "sj_nm": "자본변동표",
    "account_id": "dart_EquityAtBeginningOfPeriod",
    "account_nm": "기초자본",
    "account_detail": "자본 [member]|지배기업의 소유주에게 귀속되는 자본 [member]|이익잉여금 [member]",
    "thstrm_nm": "제 23 기 1분기",
    "thstrm_amount": "6611954196",
    "frmtrm_q_nm": "제 22 기 1분기",
    "frmtrm_q_amount": "4209020930",
    "ord": "1",
    "currency": "KRW"
  },
  {
    "rcept_no": "20220516000629",
    "reprt_code": "11013",
    "bsns_year": "2022",
    "corp_code": "00493510",
    "sj_div": "SCE",
    "sj_nm": "자본변동표",
    "account_id": "dart_EquityAtBeginningOfPeriod",
    "account_nm": "기초자본",
    "account_detail": "자본 [member]|지배기업의 소유주에게 귀속되는 자본 [member]|기타포괄손익누계액 [member]",
    "thstrm_nm": "제 23 기 1분기",
    "thstrm_amount": "10916944656",
    "frmtrm_q_nm": "제 22 기 1분기",
    "frmtrm_q_amount": "6750406194",
    "ord": "1",
    "currency": "KRW"
  },
  {
    "rcept_no": "20220516000629",
    "reprt_code": "11013",
    "bsns_year": "2022",
    "corp_code": "00493510",
    "sj_div": "SCE",
    "sj_nm": "자본변동표",
    "account_id": "dart_EquityAtBeginningOfPeriod",
    "account_nm": "기초자본",
    "account_detail": "자본 [member]|지배기업의 소유주에게 귀속되는 자본 [member]|기타자본구성요소 [member]",
    "thstrm_nm": "제 23 기 1분기",
    "thstrm_amount": "840062765",
    "frmtrm_q_nm": "제 22 기 1분기",
    "frmtrm_q_amount": "1685238975",
    "ord": "1",
    "currency": "KRW"
  },
  {
    "rcept_no": "20220516000629",
    "reprt_code": "11013",
    "bsns_year": "2022",
    "corp_code": "00493510",
    "sj_div": "SCE",
    "sj_nm": "자본변동표",
    "account_id": "dart_EquityAtBeginningOfPeriod",
    "account_nm": "기초자본",
    "account_detail": "자본 [member]|비지배지분 [member]",
    "thstrm_nm": "제 23 기 1분기",
    "thstrm_amount": "1309199602",
    "frmtrm_q_nm": "제 22 기 1분기",
    "frmtrm_q_amount": "1066274340",
    "ord": "1",
    "currency": "KRW"
  },
  {
    "rcept_no": "20220516000629",
    "reprt_code": "11013",
    "bsns_year": "2022",
    "corp_code": "00493510",
    "sj_div": "SCE",
    "sj_nm": "자본변동표",
    "account_id": "dart_EquityAtBeginningOfPeriod",
    "account_nm": "기초자본",
    "account_detail": "연결재무제표 [member]",
    "thstrm_nm": "제 23 기 1분기",
    "thstrm_amount": "52329866126",
    "frmtrm_q_nm": "제 22 기 1분기",
    "frmtrm_q_amount": "39783314952",
    "ord": "1",
    "currency": "KRW"
  },
  {
    "rcept_no": "20220516000629",
    "reprt_code": "11013",
    "bsns_year": "2022",
    "corp_code": "00493510",
    "sj_div": "SCE",
    "sj_nm": "자본변동표",
    "account_id": "-표준계정코드 미사용-",
    "account_nm": "당기순이익(손실)",
    "account_detail": "연결재무제표 [member]",
    "thstrm_nm": "제 23 기 1분기",
    "thstrm_amount": "7405506289",
    "frmtrm_q_nm": "제 22 기 1분기",
    "frmtrm_q_amount": "-1204733777",
    "ord": "3",
    "currency": "KRW"
  },
  {
    "rcept_no": "20220516000629",
    "reprt_code": "11013",
    "bsns_year": "2022",
    "corp_code": "00493510",
    "sj_div": "SCE",
    "sj_nm": "자본변동표",
    "account_id": "-표준계정코드 미사용-",
    "account_nm": "당기순이익(손실)",
    "account_detail": "자본 [member]|비지배지분 [member]",
    "thstrm_nm": "제 23 기 1분기",
    "thstrm_amount": "28968677",
    "frmtrm_q_nm": "제 22 기 1분기",
    "frmtrm_q_amount": "-72083017",
    "ord": "3",
    "currency": "KRW"
  },
  {
    "rcept_no": "20220516000629",
    "reprt_code": "11013",
    "bsns_year": "2022",
    "corp_code": "00493510",
    "sj_div": "SCE",
    "sj_nm": "자본변동표",
    "account_id": "-표준계정코드 미사용-",
    "account_nm": "당기순이익(손실)",
    "account_detail": "자본 [member]|지배기업의 소유주에게 귀속되는 자본 [member]",
    "thstrm_nm": "제 23 기 1분기",
    "thstrm_amount": "7376537612",
    "frmtrm_q_nm": "제 22 기 1분기",
    "frmtrm_q_amount": "-1132650760",
    "ord": "3",
    "currency": "KRW"
  },
  {
    "rcept_no": "20220516000629",
    "reprt_code": "11013",
    "bsns_year": "2022",
    "corp_code": "00493510",
    "sj_div": "SCE",
    "sj_nm": "자본변동표",
    "account_id": "-표준계정코드 미사용-",
    "account_nm": "당기순이익(손실)",
    "account_detail": "자본 [member]|지배기업의 소유주에게 귀속되는 자본 [member]|이익잉여금 [member]",
    "thstrm_nm": "제 23 기 1분기",
    "thstrm_amount": "7376537612",
    "frmtrm_q_nm": "제 22 기 1분기",
    "frmtrm_q_amount": "-1132650760",
    "ord": "3",
    "currency": "KRW"
  },
  {
    "rcept_no": "20220516000629",
    "reprt_code": "11013",
    "bsns_year": "2022",
    "corp_code": "00493510",
    "sj_div": "SCE",
    "sj_nm": "자본변동표",
    "account_id": "-표준계정코드 미사용-",
    "account_nm": "보험수리적손익",
    "account_detail": "자본 [member]|지배기업의 소유주에게 귀속되는 자본 [member]",
    "thstrm_nm": "제 23 기 1분기",
    "thstrm_amount": "",
    "frmtrm_q_nm": "제 22 기 1분기",
    "frmtrm_q_amount": "8980788",
    "ord": "5",
    "currency": "KRW"
  },
  {
    "rcept_no": "20220516000629",
    "reprt_code": "11013",
    "bsns_year": "2022",
    "corp_code": "00493510",
    "sj_div": "SCE",
    "sj_nm": "자본변동표",
    "account_id": "-표준계정코드 미사용-",
    "account_nm": "보험수리적손익",
    "account_detail": "자본 [member]|비지배지분 [member]",
    "thstrm_nm": "제 23 기 1분기",
    "thstrm_amount": "",
    "frmtrm_q_nm": "제 22 기 1분기",
    "frmtrm_q_amount": "16778078",
    "ord": "5",
    "currency": "KRW"
  },
  {
    "rcept_no": "20220516000629",
    "reprt_code": "11013",
    "bsns_year": "2022",
    "corp_code": "00493510",
    "sj_div": "SCE",
    "sj_nm": "자본변동표",
    "account_id": "-표준계정코드 미사용-",
    "account_nm": "보험수리적손익",
    "account_detail": "연결재무제표 [member]",
    "thstrm_nm": "제 23 기 1분기",
    "thstrm_amount": "",
    "frmtrm_q_nm": "제 22 기 1분기",
    "frmtrm_q_amount": "25758866",
    "ord": "5",
    "currency": "KRW"
  },
  {
    "rcept_no": "20220516000629",
    "reprt_code": "11013",
    "bsns_year": "2022",
    "corp_code": "00493510",
    "sj_div": "SCE",
    "sj_nm": "자본변동표",
    "account_id": "-표준계정코드 미사용-",
    "account_nm": "보험수리적손익",
    "account_detail": "자본 [member]|지배기업의 소유주에게 귀속되는 자본 [member]|이익잉여금 [member]",
    "thstrm_nm": "제 23 기 1분기",
    "thstrm_amount": "",
    "frmtrm_q_nm": "제 22 기 1분기",
    "frmtrm_q_amount": "8980788",
    "ord": "5",
    "currency": "KRW"
  },
  {
    "rcept_no": "20220516000629",
    "reprt_code": "11013",
    "bsns_year": "2022",
    "corp_code": "00493510",
    "sj_div": "SCE",
    "sj_nm": "자본변동표",
    "account_id": "-표준계정코드 미사용-",
    "account_nm": "해외사업환산증감",
    "account_detail": "연결재무제표 [member]",
    "thstrm_nm": "제 23 기 1분기",
    "thstrm_amount": "-120150306",
    "frmtrm_q_nm": "제 22 기 1분기",
    "frmtrm_q_amount": "192670086",
    "ord": "6",
    "currency": "KRW"
  },
  {
    "rcept_no": "20220516000629",
    "reprt_code": "11013",
    "bsns_year": "2022",
    "corp_code": "00493510",
    "sj_div": "SCE",
    "sj_nm": "자본변동표",
    "account_id": "-표준계정코드 미사용-",
    "account_nm": "해외사업환산증감",
    "account_detail": "자본 [member]|지배기업의 소유주에게 귀속되는 자본 [member]",
    "thstrm_nm": "제 23 기 1분기",
    "thstrm_amount": "-120150306",
    "frmtrm_q_nm": "제 22 기 1분기",
    "frmtrm_q_amount": "192670086",
    "ord": "6",
    "currency": "KRW"
  },
  {
    "rcept_no": "20220516000629",
    "reprt_code": "11013",
    "bsns_year": "2022",
    "corp_code": "00493510",
    "sj_div": "SCE",
    "sj_nm": "자본변동표",
    "account_id": "-표준계정코드 미사용-",
    "account_nm": "해외사업환산증감",
    "account_detail": "자본 [member]|지배기업의 소유주에게 귀속되는 자본 [member]|기타포괄손익누계액 [member]",
    "thstrm_nm": "제 23 기 1분기",
    "thstrm_amount": "-120150306",
    "frmtrm_q_nm": "제 22 기 1분기",
    "frmtrm_q_amount": "192670086",
    "ord": "6",
    "currency": "KRW"
  },
  {
    "rcept_no": "20220516000629",
    "reprt_code": "11013",
    "bsns_year": "2022",
    "corp_code": "00493510",
    "sj_div": "SCE",
    "sj_nm": "자본변동표",
    "account_id": "-표준계정코드 미사용-",
    "account_nm": "주식매입선택권",
    "account_detail": "자본 [member]|지배기업의 소유주에게 귀속되는 자본 [member]",
    "thstrm_nm": "제 23 기 1분기",
    "thstrm_amount": "7978069",
    "frmtrm_q_nm": "제 22 기 1분기",
    "ord": "7",
    "currency": "KRW"
  },
  {
    "rcept_no": "20220516000629",
    "reprt_code": "11013",
    "bsns_year": "2022",
    "corp_code": "00493510",
    "sj_div": "SCE",
    "sj_nm": "자본변동표",
    "account_id": "-표준계정코드 미사용-",
    "account_nm": "주식매입선택권",
    "account_detail": "자본 [member]|지배기업의 소유주에게 귀속되는 자본 [member]|기타자본구성요소 [member]",
    "thstrm_nm": "제 23 기 1분기",
    "thstrm_amount": "7978069",
    "frmtrm_q_nm": "제 22 기 1분기",
    "frmtrm_q_amount": "-103606249",
    "ord": "7",
    "currency": "KRW"
  },
  {
    "rcept_no": "20220516000629",
    "reprt_code": "11013",
    "bsns_year": "2022",
    "corp_code": "00493510",
    "sj_div": "SCE",
    "sj_nm": "자본변동표",
    "account_id": "-표준계정코드 미사용-",
    "account_nm": "주식매입선택권",
    "account_detail": "자본 [member]|지배기업의 소유주에게 귀속되는 자본 [member]|자본잉여금 [member]",
    "thstrm_nm": "제 23 기 1분기",
    "thstrm_amount": "",
    "frmtrm_q_nm": "제 22 기 1분기",
    "frmtrm_q_amount": "103606249",
    "ord": "7",
    "currency": "KRW"
  },
  {
    "rcept_no": "20220516000629",
    "reprt_code": "11013",
    "bsns_year": "2022",
    "corp_code": "00493510",
    "sj_div": "SCE",
    "sj_nm": "자본변동표",
    "account_id": "-표준계정코드 미사용-",
    "account_nm": "주식매입선택권",
    "account_detail": "연결재무제표 [member]",
    "thstrm_nm": "제 23 기 1분기",
    "thstrm_amount": "7978069",
    "frmtrm_q_nm": "제 22 기 1분기",
    "ord": "7",
    "currency": "KRW"
  },
  {
    "rcept_no": "20220516000629",
    "reprt_code": "11013",
    "bsns_year": "2022",
    "corp_code": "00493510",
    "sj_div": "SCE",
    "sj_nm": "자본변동표",
    "account_id": "dart_CompoundFinancialInstrumentConversion",
    "account_nm": "전환사채 주식전환",
    "account_detail": "자본 [member]|지배기업의 소유주에게 귀속되는 자본 [member]",
    "thstrm_nm": "제 23 기 1분기",
    "thstrm_amount": "",
    "frmtrm_q_nm": "제 22 기 1분기",
    "frmtrm_q_amount": "701850021",
    "ord": "8",
    "currency": "KRW"
  },
  {
    "rcept_no": "20220516000629",
    "reprt_code": "11013",
    "bsns_year": "2022",
    "corp_code": "00493510",
    "sj_div": "SCE",
    "sj_nm": "자본변동표",
    "account_id": "dart_CompoundFinancialInstrumentConversion",
    "account_nm": "전환사채 주식전환",
    "account_detail": "연결재무제표 [member]",
    "thstrm_nm": "제 23 기 1분기",
    "thstrm_amount": "",
    "frmtrm_q_nm": "제 22 기 1분기",
    "frmtrm_q_amount": "701850021",
    "ord": "8",
    "currency": "KRW"
  },
  {
    "rcept_no": "20220516000629",
    "reprt_code": "11013",
    "bsns_year": "2022",
    "corp_code": "00493510",
    "sj_div": "SCE",
    "sj_nm": "자본변동표",
    "account_id": "dart_CompoundFinancialInstrumentConversion",
    "account_nm": "전환사채 주식전환",
    "account_detail": "자본 [member]|지배기업의 소유주에게 귀속되는 자본 [member]|자본금 [member]",
    "thstrm_nm": "제 23 기 1분기",
    "thstrm_amount": "",
    "frmtrm_q_nm": "제 22 기 1분기",
    "frmtrm_q_amount": "137361443",
    "ord": "8",
    "currency": "KRW"
  },
  {
    "rcept_no": "20220516000629",
    "reprt_code": "11013",
    "bsns_year": "2022",
    "corp_code": "00493510",
    "sj_div": "SCE",
    "sj_nm": "자본변동표",
    "account_id": "dart_CompoundFinancialInstrumentConversion",
    "account_nm": "전환사채 주식전환",
    "account_detail": "자본 [member]|지배기업의 소유주에게 귀속되는 자본 [member]|자본잉여금 [member]",
    "thstrm_nm": "제 23 기 1분기",
    "thstrm_amount": "",
    "frmtrm_q_nm": "제 22 기 1분기",
    "frmtrm_q_amount": "564488578",
    "ord": "8",
    "currency": "KRW"
  },
  {
    "rcept_no": "20220516000629",
    "reprt_code": "11013",
    "bsns_year": "2022",
    "corp_code": "00493510",
    "sj_div": "SCE",
    "sj_nm": "자본변동표",
    "account_id": "ifrs-full_Equity",
    "account_nm": "기말자본",
    "account_detail": "자본 [member]|지배기업의 소유주에게 귀속되는 자본 [member]",
    "thstrm_nm": "제 23 기 1분기",
    "thstrm_amount": "58636349162",
    "frmtrm_q_nm": "제 22 기 1분기",
    "frmtrm_q_amount": "38344664281",
    "ord": "9",
    "currency": "KRW"
  },
  {
    "rcept_no": "20220516000629",
    "reprt_code": "11013",
    "bsns_year": "2022",
    "corp_code": "00493510",
    "sj_div": "SCE",
    "sj_nm": "자본변동표",
    "account_id": "ifrs-full_Equity",
    "account_nm": "기말자본",
    "account_detail": "자본 [member]|지배기업의 소유주에게 귀속되는 자본 [member]|자본잉여금 [member]",
    "thstrm_nm": "제 23 기 1분기",
    "thstrm_amount": "20546908407",
    "frmtrm_q_nm": "제 22 기 1분기",
    "frmtrm_q_amount": "15855673283",
    "ord": "9",
    "currency": "KRW"
  },
  {
    "rcept_no": "20220516000629",
    "reprt_code": "11013",
    "bsns_year": "2022",
    "corp_code": "00493510",
    "sj_div": "SCE",
    "sj_nm": "자본변동표",
    "account_id": "ifrs-full_Equity",
    "account_nm": "기말자본",
    "account_detail": "자본 [member]|비지배지분 [member]",
    "thstrm_nm": "제 23 기 1분기",
    "thstrm_amount": "1338088279",
    "frmtrm_q_nm": "제 22 기 1분기",
    "frmtrm_q_amount": "1010969401",
    "ord": "9",
    "currency": "KRW"
  },
  {
    "rcept_no": "20220516000629",
    "reprt_code": "11013",
    "bsns_year": "2022",
    "corp_code": "00493510",
    "sj_div": "SCE",
    "sj_nm": "자본변동표",
    "account_id": "ifrs-full_Equity",
    "account_nm": "기말자본",
    "account_detail": "연결재무제표 [member]",
    "thstrm_nm": "제 23 기 1분기",
    "thstrm_amount": "59623200177",
    "frmtrm_q_nm": "제 22 기 1분기",
    "frmtrm_q_amount": "39355633682",
    "ord": "9",
    "currency": "KRW"
  },
  {
    "rcept_no": "20220516000629",
    "reprt_code": "11013",
    "bsns_year": "2022",
    "corp_code": "00493510",
    "sj_div": "SCE",
    "sj_nm": "자본변동표",
    "account_id": "ifrs-full_Equity",
    "account_nm": "기말자본",
    "account_detail": "자본 [member]|지배기업의 소유주에게 귀속되는 자본 [member]|기타자본구성요소 [member]",
    "thstrm_nm": "제 23 기 1분기",
    "thstrm_amount": "848040834",
    "frmtrm_q_nm": "제 22 기 1분기",
    "frmtrm_q_amount": "1438406260",
    "ord": "9",
    "currency": "KRW"
  },
  {
    "rcept_no": "20220516000629",
    "reprt_code": "11013",
    "bsns_year": "2022",
    "corp_code": "00493510",
    "sj_div": "SCE",
    "sj_nm": "자본변동표",
    "account_id": "ifrs-full_Equity",
    "account_nm": "기말자본",
    "account_detail": "자본 [member]|지배기업의 소유주에게 귀속되는 자본 [member]|기타포괄손익누계액 [member]",
    "thstrm_nm": "제 23 기 1분기",
    "thstrm_amount": "10796794350",
    "frmtrm_q_nm": "제 22 기 1분기",
    "frmtrm_q_amount": "6943076280",
    "ord": "9",
    "currency": "KRW"
  },
  {
    "rcept_no": "20220516000629",
    "reprt_code": "11013",
    "bsns_year": "2022",
    "corp_code": "00493510",
    "sj_div": "SCE",
    "sj_nm": "자본변동표",
    "account_id": "ifrs-full_Equity",
    "account_nm": "기말자본",
    "account_detail": "자본 [member]|지배기업의 소유주에게 귀속되는 자본 [member]|이익잉여금 [member]",
    "thstrm_nm": "제 23 기 1분기",
    "thstrm_amount": "13988491808",
    "frmtrm_q_nm": "제 22 기 1분기",
    "frmtrm_q_amount": "3085350958",
    "ord": "9",
    "currency": "KRW"
  },
  {
    "rcept_no": "20220516000629",
    "reprt_code": "11013",
    "bsns_year": "2022",
    "corp_code": "00493510",
    "sj_div": "SCE",
    "sj_nm": "자본변동표",
    "account_id": "ifrs-full_Equity",
    "account_nm": "기말자본",
    "account_detail": "자본 [member]|지배기업의 소유주에게 귀속되는 자본 [member]|자본금 [member]",
    "thstrm_nm": "제 23 기 1분기",
    "thstrm_amount": "12104876500",
    "frmtrm_q_nm": "제 22 기 1분기",
    "frmtrm_q_amount": "11022157500",
    "ord": "9",
    "currency": "KRW"
  }
]